Metadata-Version: 2.1
Name: oligopipe
Version: 1.1.3
Summary: Python package for Oligogenic Variant Analysis pipelines
Home-page: https://oligogenic.github.io/oligopipe-docs/
Author: Interuniversity Institute of Bioinformatics Brussels
Author-email: oligopipe@ibsquare.be
Maintainer: Emma Verkinderen
Maintainer-email: oligopipe@ibsquare.be
License: MIT
Classifier: Programming Language :: Python :: 3.8
Classifier: Programming Language :: Python :: 3.9
Classifier: Programming Language :: Python :: 3.10
Classifier: License :: OSI Approved :: MIT License
Classifier: Operating System :: Unix
Classifier: Operating System :: MacOS :: MacOS X
Classifier: Intended Audience :: Science/Research
Classifier: Topic :: Scientific/Engineering :: Bio-Informatics
License-File: LICENSE
Requires-Dist: numpy
Requires-Dist: python-magic
Requires-Dist: networkx
Requires-Dist: psycopg2-binary
Requires-Dist: psycopg2
Requires-Dist: treeinterpreter
Requires-Dist: scikit-learn ==1.1.0
Requires-Dist: imbalanced-learn ==0.9.1
Requires-Dist: pyyaml
